slack_notifications/__init__.py
slack_notifications/common.py
slack_notifications/constants.py
slack_notifications/utils.py
slack_notifications/fields/__init__.py
slack_notifications/fields/attachments.py
slack_notifications/fields/blocks.py
slack_notifications/fields/mrkdwn.py
slack_notifications/interfaces/__init__.py
slack_notifications/interfaces/client.py
slack_notifications/mattermost/__init__.py
slack_notifications/mattermost/client.py
slack_notifications/mattermost/converter.py
slack_notifications/mattermost/fields/__init__.py
slack_notifications/mattermost/fields/mrkdwn.py
slack_notifications/slack/__init__.py
slack_notifications/slack/client.py
slack_notifications-1.0.1.dist-info/METADATA
slack_notifications-1.0.1.dist-info/WHEEL
slack_notifications-1.0.1.dist-info/top_level.txt
slack_notifications-1.0.1.dist-info/RECORD
