Metadata-Version: 2.1
Name: slack-notifications
Version: 1.0.1
Summary: Send notifications to slack channel with supporting attachments and fields
Home-page: https://github.com/qa-team-tools/slack-notifications
Author: Mikhail Trifonov
Author-email: trifonov.net@gmail.com
Keywords: slack notifications
Classifier: Development Status :: 4 - Beta
Classifier: Intended Audience :: Developers
Classifier: Operating System :: POSIX
Classifier: Operating System :: Microsoft :: Windows
Classifier: Operating System :: MacOS :: MacOS X
Classifier: Topic :: Utilities
Classifier: Programming Language :: Python :: 3.6
Classifier: Programming Language :: Python :: 3.7
Classifier: Programming Language :: Python :: 3.8
Classifier: Programming Language :: Python :: Implementation :: CPython
Requires-Dist: requests
